faker_stalker_names/__init__.py
faker_stalker_names/de_DE/__init__.py
faker_stalker_names/de_DE/data.py
faker_stalker_names/en_US/__init__.py
faker_stalker_names/en_US/data.py
faker_stalker_names/es_ES/__init__.py
faker_stalker_names/es_ES/data.py
faker_stalker_names/fr_FR/__init__.py
faker_stalker_names/fr_FR/data.py
faker_stalker_names/it_IT/__init__.py
faker_stalker_names/it_IT/data.py
faker_stalker_names/pl_PL/__init__.py
faker_stalker_names/pl_PL/data.py
faker_stalker_names/ru_RU/__init__.py
faker_stalker_names/ru_RU/data.py
faker_stalker_names/uk_UA/__init__.py
faker_stalker_names/uk_UA/data.py
faker_stalker_names-0.1.4.dist-info/LICENSE
faker_stalker_names-0.1.4.dist-info/WHEEL
faker_stalker_names-0.1.4.dist-info/METADATA
faker_stalker_names-0.1.4.dist-info/RECORD
