Metadata-Version: 2.1
Name: faker-stalker-names
Version: 0.1.4
Summary: Faker provider to generate stalker names.
Home-page: https://github.com/booqoffsky/faker-stalker-names
License: MIT
Keywords: faker,fun,stalker,provider,generator
Author: Grigory Bukovsky
Author-email: booqoffsky@yandex.ru
Requires-Python: >=3.7,<4.0
Classifier: License :: OSI Approved :: MIT License
Classifier: Programming Language :: Python :: 3
Classifier: Programming Language :: Python :: 3.7
Classifier: Programming Language :: Python :: 3.8
Classifier: Programming Language :: Python :: 3.9
Classifier: Programming Language :: Python :: 3.10
Project-URL: Repository, https://github.com/booqoffsky/faker-stalker-names
